fbp/__init__.py
fbp/__main__.py
fbp/builder.py
fbp/parser.py
fbp-1.3.6.dist-info/LICENSE
fbp-1.3.6.dist-info/METADATA
fbp-1.3.6.dist-info/WHEEL
fbp-1.3.6.dist-info/entry_points.txt
fbp-1.3.6.dist-info/top_level.txt
fbp-1.3.6.dist-info/RECORD
